phxd/__init__.py
phxd/constants.py
phxd/packet.py
phxd/permissions.py
phxd/protocol.py
phxd/transfer.py
phxd/types.py
phxd/utils.py
phxd/client/__init__.py
phxd/client/signals.py
phxd/server/__init__.py
phxd/server/decorators.py
phxd/server/files.py
phxd/server/signals.py
phxd/server/utils.py
phxd/server/commands/__init__.py
phxd/server/commands/away.py
phxd/server/commands/broadcast.py
phxd/server/commands/find.py
phxd/server/commands/handler.py
phxd/server/commands/kick.py
phxd/server/commands/me.py
phxd/server/commands/mimic.py
phxd/server/commands/setcolor.py
phxd/server/commands/setdefaulticon.py
phxd/server/commands/seticon.py
phxd/server/commands/uptime.py
phxd/server/commands/xfers.py
phxd/server/config/__init__.py
phxd/server/config/default.py
phxd/server/database/__init__.py
phxd/server/database/sqlite.py
phxd/server/database/text.py
phxd/server/handlers/__init__.py
phxd/server/handlers/account.py
phxd/server/handlers/chat.py
phxd/server/handlers/files.py
phxd/server/handlers/icon.py
phxd/server/handlers/logger.py
phxd/server/handlers/message.py
phxd/server/handlers/news.py
phxd/server/handlers/user.py
phxd/tracker/__init__.py
phxd/tracker/protocol.py
phxd-1.0.2.data/scripts/phx
phxd-1.0.2.data/scripts/phxd
phxd-1.0.2.dist-info/LICENSE
phxd-1.0.2.dist-info/METADATA
phxd-1.0.2.dist-info/WHEEL
phxd-1.0.2.dist-info/top_level.txt
phxd-1.0.2.dist-info/RECORD
