Metadata-Version: 2.1
Name: phxd
Version: 1.0.2
Summary: A Hotline server written in Python using Twisted.
Home-page: https://github.com/dcwatson/phxd
Author: Dan Watson
Author-email: dcwatson@gmail.com
License: BSD
Platform: UNKNOWN
Classifier: Development Status :: 4 - Beta
Classifier: License :: OSI Approved :: BSD License
Classifier: Operating System :: OS Independent
Classifier: Programming Language :: Python
Requires-Dist: PyDispatcher
Requires-Dist: pyOpenSSL
Requires-Dist: service-identity
Requires-Dist: Twisted
